PythonZiranyuyanChuliDierBanFix1Fix1/README.md
PythonZiranyuyanChuliDierBanFix1Fix1/__init__.py
PythonZiranyuyanChuliDierBanFix1Fix1/__main__.py
PythonZiranyuyanChuliDierBanFix1Fix1/file.epub
PythonZiranyuyanChuliDierBanFix1Fix1/index.html
PythonZiranyuyanChuliDierBanFix1Fix1/css/__init__.py
PythonZiranyuyanChuliDierBanFix1Fix1/css/annotations.css
PythonZiranyuyanChuliDierBanFix1Fix1/css/main.css
PythonZiranyuyanChuliDierBanFix1Fix1/css/normalize.css
PythonZiranyuyanChuliDierBanFix1Fix1/css/popup.css
PythonZiranyuyanChuliDierBanFix1Fix1/font/__init__.py
PythonZiranyuyanChuliDierBanFix1Fix1/font/fontello.eot
PythonZiranyuyanChuliDierBanFix1Fix1/font/fontello.svg
PythonZiranyuyanChuliDierBanFix1Fix1/font/fontello.ttf
PythonZiranyuyanChuliDierBanFix1Fix1/font/fontello.woff
PythonZiranyuyanChuliDierBanFix1Fix1/img/__init__.py
PythonZiranyuyanChuliDierBanFix1Fix1/img/annotator-glyph-sprite.png
PythonZiranyuyanChuliDierBanFix1Fix1/img/annotator-icon-sprite.png
PythonZiranyuyanChuliDierBanFix1Fix1/img/apple-touch-icon.png
PythonZiranyuyanChuliDierBanFix1Fix1/img/cancelfullscreen.png
PythonZiranyuyanChuliDierBanFix1Fix1/img/close.png
PythonZiranyuyanChuliDierBanFix1Fix1/img/fullscreen.png
PythonZiranyuyanChuliDierBanFix1Fix1/img/loader.gif
PythonZiranyuyanChuliDierBanFix1Fix1/img/menu-icon.png
PythonZiranyuyanChuliDierBanFix1Fix1/img/save.png
PythonZiranyuyanChuliDierBanFix1Fix1/img/saved.png
PythonZiranyuyanChuliDierBanFix1Fix1/img/settings-s.png
PythonZiranyuyanChuliDierBanFix1Fix1/img/settings.png
PythonZiranyuyanChuliDierBanFix1Fix1/img/star.png
PythonZiranyuyanChuliDierBanFix1Fix1/js/__init__.py
PythonZiranyuyanChuliDierBanFix1Fix1/js/epub.js
PythonZiranyuyanChuliDierBanFix1Fix1/js/epub.min.js
PythonZiranyuyanChuliDierBanFix1Fix1/js/epub.min.map
PythonZiranyuyanChuliDierBanFix1Fix1/js/hooks.min.js
PythonZiranyuyanChuliDierBanFix1Fix1/js/hooks.min.map
PythonZiranyuyanChuliDierBanFix1Fix1/js/reader.js
PythonZiranyuyanChuliDierBanFix1Fix1/js/reader.js.map
python_ziranyuyan_chuli_dier_ban_fix1_fix1-2025.3.25.0.dist-info/METADATA
python_ziranyuyan_chuli_dier_ban_fix1_fix1-2025.3.25.0.dist-info/WHEEL
python_ziranyuyan_chuli_dier_ban_fix1_fix1-2025.3.25.0.dist-info/entry_points.txt
python_ziranyuyan_chuli_dier_ban_fix1_fix1-2025.3.25.0.dist-info/top_level.txt
python_ziranyuyan_chuli_dier_ban_fix1_fix1-2025.3.25.0.dist-info/RECORD
